github2gerrit/__init__.py
github2gerrit/cli.py
github2gerrit/commit_normalization.py
github2gerrit/config.py
github2gerrit/constants.py
github2gerrit/core.py
github2gerrit/duplicate_detection.py
github2gerrit/error_codes.py
github2gerrit/external_api.py
github2gerrit/gerrit_pr_closer.py
github2gerrit/gerrit_query.py
github2gerrit/gerrit_rest.py
github2gerrit/gerrit_urls.py
github2gerrit/github_api.py
github2gerrit/gitutils.py
github2gerrit/mapping_comment.py
github2gerrit/models.py
github2gerrit/pr_content_filter.py
github2gerrit/reconcile_matcher.py
github2gerrit/rich_display.py
github2gerrit/rich_logging.py
github2gerrit/similarity.py
github2gerrit/ssh_agent_setup.py
github2gerrit/ssh_common.py
github2gerrit/ssh_config_parser.py
github2gerrit/ssh_discovery.py
github2gerrit/trailers.py
github2gerrit/utils.py
github2gerrit/orchestrator/__init__.py
github2gerrit/orchestrator/reconciliation.py
github2gerrit-1.0.3.dist-info/METADATA
github2gerrit-1.0.3.dist-info/WHEEL
github2gerrit-1.0.3.dist-info/entry_points.txt
github2gerrit-1.0.3.dist-info/licenses/LICENSE
github2gerrit-1.0.3.dist-info/RECORD
