Metadata-Version: 2.4
Name: github2gerrit
Version: 1.0.3
Summary: Submit a GitHub pull request to a Gerrit repository.
Project-URL: Homepage, https://github.com/lfreleng-actions/github2gerrit-action
Project-URL: Repository, https://github.com/lfreleng-actions/github2gerrit-action
Project-URL: Issues, https://github.com/lfreleng-actions/github2gerrit-action/issues
Author-email: Matthew Watkins <mwatkins@linuxfoundation.org>
License-Expression: Apache-2.0
License-File: LICENSE
Keywords: actions,ci,cli,gerrit,github,typer
Classifier: Development Status :: 4 - Beta
Classifier: Environment :: Console
Classifier: Intended Audience :: Developers
Classifier: Programming Language :: Python :: 3
Classifier: Programming Language :: Python :: 3 :: Only
Classifier: Programming Language :: Python :: 3.11
Classifier: Programming Language :: Python :: 3.12
Classifier: Programming Language :: Python :: 3.13
Classifier: Programming Language :: Python :: 3.14
Classifier: Topic :: Software Development :: Build Tools
Classifier: Topic :: Software Development :: Version Control
Classifier: Typing :: Typed
Requires-Python: >=3.11
Requires-Dist: git-review>=2.5.0
Requires-Dist: pygerrit2>=2.0.15
Requires-Dist: pygithub>=2.8.1
Requires-Dist: pynacl>=1.6.2
Requires-Dist: pyyaml>=6.0.3
Requires-Dist: rich>=14.2.0
Requires-Dist: typer>=0.20.1
Requires-Dist: urllib3>=2.6.3
Provides-Extra: dev
Requires-Dist: coverage[toml]>=7.10.6; extra == 'dev'
Requires-Dist: mypy>=1.17.1; extra == 'dev'
Requires-Dist: pytest-cov>=7.0.0; extra == 'dev'
Requires-Dist: pytest-mock>=3.15.1; extra == 'dev'
Requires-Dist: pytest>=9.0.2; extra == 'dev'
Requires-Dist: responses>=0.25.8; extra == 'dev'
Requires-Dist: ruff>=0.6.3; extra == 'dev'
Requires-Dist: types-click>=7.1.8; extra == 'dev'
Requires-Dist: types-requests>=2.31.0; extra == 'dev'
Requires-Dist: types-urllib3>=1.26.25.14; extra == 'dev'
